{"stat.craftItem.minecraft.leather_leggings":2,"stat.useItem.minecraft.bow":152,"stat.useItem.minecraft.lapis_block":20,"stat.useItem.minecraft.sticky_piston":5,"stat.useItem.minecraft.stone":74,"stat.leaveGame":38,"stat.mineBlock.minecraft.pumpkin":1,"stat.mineBlock.minecraft.slime":78,"stat.useItem.minecraft.diamond_axe":28,"stat.useItem.minecraft.diamond_sword":104,"stat.useItem.minecraft.potion":8,"stat.useItem.minecraft.glowstone":17,"stat.jump":830,"stat.swimOneCm":22593,"stat.climbOneCm":12635,"stat.fallOneCm":19642,"stat.crouchOneCm":1782,"stat.enderchestOpened":1,"stat.craftItem.minecraft.banner":4,"achievement.exploreAllBiomes":{"value":0,"progress":["River","Forest","Plains","Extreme Hills"]},"stat.craftingTableInteraction":19,"stat.useItem.minecraft.iron_ore":9,"stat.damageTaken":102618,"stat.useItem.minecraft.slime":99,"stat.flyOneCm":334762,"stat.useItem.minecraft.cooked_beef":1,"stat.damageDealt":13879,"stat.killEntity.Rabbit":6,"stat.useItem.minecraft.wool":29,"stat.timeSinceDeath":29232,"stat.useItem.minecraft.crafting_table":4,"stat.useItem.minecraft.sign":1,"stat.useItem.minecraft.spawn_egg":9,"stat.walkOneCm":947779,"stat.useItem.minecraft.pumpkin":1,"stat.useItem.minecraft.cobblestone":23,"stat.craftItem.minecraft.leather_boots":1,"stat.craftItem.minecraft.leather_helmet":1,"stat.useItem.minecraft.sea_lantern":15,"stat.useItem.minecraft.milk_bucket":6,"stat.sprintOneCm":262498,"stat.useItem.minecraft.stained_glass":3,"stat.useItem.minecraft.fence":6,"stat.useItem.minecraft.stone_stairs":6,"stat.breakItem.minecraft.diamond_helmet":1,"stat.useItem.minecraft.prismarine":212,"achievement.openInventory":353,"stat.mineBlock.minecraft.stonebrick":1,"stat.useItem.minecraft.iron_sword":11,"stat.mineBlock.minecraft.crafting_table":1,"stat.useItem.minecraft.stone_pressure_plate":1,"stat.useItem.minecraft.diamond_pickaxe":51,"stat.mobKills":6,"stat.useItem.minecraft.stonebrick":35,"stat.useItem.minecraft.bucket":1,"stat.useItem.minecraft.golden_apple":38,"stat.deaths":24,"stat.useItem.minecraft.spruce_door":1,"stat.drop":23,"stat.playOneMinute":350356,"stat.craftItem.minecraft.leather_chestplate":2,"stat.useItem.minecraft.banner":6,"stat.mineBlock.minecraft.stone":45}