{"stat.useItem.minecraft.iron_bars":1,"stat.beaconInteraction":1,"stat.walkOneCm":182294,"stat.leaveGame":37,"stat.useItem.minecraft.potion":238,"stat.mineBlock.minecraft.stained_glass":1,"stat.jump":596,"stat.swimOneCm":2350,"stat.useItem.minecraft.sand":1,"stat.fallOneCm":7647,"stat.climbOneCm":6688,"stat.crouchOneCm":13025,"stat.sprintOneCm":66868,"achievement.exploreAllBiomes":{"value":0,"progress":["Deep Ocean"]},"stat.mineBlock.minecraft.iron_bars":2,"achievement.openInventory":10,"stat.useItem.minecraft.barrier":2,"stat.damageTaken":655538,"stat.flyOneCm":168806,"stat.deaths":5,"stat.drop":4,"stat.mineBlock.minecraft.sand":1,"stat.playOneMinute":69017,"stat.useItem.minecraft.stone_pickaxe":3,"stat.mineBlock.minecraft.glass":1,"stat.timeSinceDeath":24281,"stat.diveOneCm":6557}